fifth.v

module fifth(
    // Standard inputs
    input  wire clk, reset,
    // Instruction + instruction address
    output wire [12:0] code_addr,
    input  wire [15:0] instruction,
    // Memory access
    output wire [15:0] mem_address,
    output wire mem_write_enable,
    input  wire [15:0] mem_data_input,
    output wire [15:0] mem_data_output
);

reg [3:0] dsp, dsp_next, rsp, rsp_next;
reg dstack_write_enable, rstack_write_enable;
wire [15:0] rstack_write_data;

reg [15:0] T, T_next;
wire [15:0] N, R;
reg [12:0] pc, pc_next;
reg reboot = 1;

fifth_stack dstack(
    .clk(clk),
    .write_enable(dstack_write_enable),
    .read_addr(dsp),
    .read_data(N),
    .write_addr(dsp_next),
    .write_data(T)
);

fifth_stack rstack(
    .clk(clk),
    .write_enable(rstack_write_enable),
    .read_addr(rsp),
    .read_data(R),
    .write_addr(rsp_next),
    .write_data(rstack_write_data)
);

assign code_addr = pc_next;
assign mem_address = T_next;
assign mem_write_enable = !reboot && (instruction[15:13] == 3'b011) && instruction[4]; // N->[T]
assign rstack_write_data = instruction[13] == 1'b0 ?  { 2'b11, pc + 12'b1, 1'b0 } : T;

always @*
begin
    casez (instruction[15:8])
        8'b1??_?????: T_next = { 1'b0, instruction[14:0] }; // immed
        8'b000_?????: T_next = T; // branch
        8'b001_?????: T_next = N; // 0branch
        8'b010_?????: T_next = T; // call
        8'b011_00000: T_next = T;
        8'b011_00001: T_next = N;
        8'b011_00010: begin
            $display("**** N(%x) + T(%x) = %x", N, T, N + T);
            T_next = N + T;
        end
        8'b011_00011: T_next = N & T;
        8'b011_00100: T_next = N | T;
        8'b011_00101: T_next = N ^ T;
        8'b011_00110: T_next = ~T;
        8'b011_00111: T_next = { 16{N == T} };
        8'b011_01000: T_next = { 16{$signed(N) < $signed(T)} };
        8'b011_01001: T_next = N >> T[4:0];
        8'b011_01010: T_next = N << T[4:0];
        8'b011_01011: T_next = R;
        8'b011_01100: T_next = mem_data_input;
        8'b011_01101: T_next = T/* TODO */;
        8'b011_01110: T_next = { {8{1'b0}}, rsp, dsp };
        8'b011_01111: T_next = { 16{N < T} };
        default: T_next = 16'bxxxxxxxxxxxxxxxx;
    endcase
end

reg [3:0] dsp_delta, rsp_delta;
always @*
begin
    casez (instruction[15:13])
        3'b1??:  {dstack_write_enable, dsp_delta} = { 1'b1, 4'b0001 };
        3'b001:  {dstack_write_enable, dsp_delta} = { 1'b0, 4'b1111 };
        3'b011:
        begin
            {dstack_write_enable, dsp_delta} = {instruction[6], {instruction[1], instruction[1], instruction[1:0]}};
            $display("instruction: %x", instruction);
            $display("instruction[6]: %x", instruction[6]);
            $display("dstack_write_enable: %x", dstack_write_enable);
        end
        default: {dstack_write_enable, dsp_delta} = { 1'b0, 4'b0000 };
        // 3'b1??: begin
        //     dstack_write_enable = 1'b1;
        //     dsp_next = dsp + 4'b0001;
        // end
        // 3'b001: begin
        //     dstack_write_enable = 1'b0;
        //     dsp_next = dsp + 4'b1111;
        // end
        // 3'b011: begin
        //     dstack_write_enable = instruction[6]; // T→N
        //     dsp_next = dsp + { instruction[1], instruction[1], instruction[1:0] }; // dstack
        // end
        // default: begin
        //     dstack_write_enable = 1'b0;
        //     dsp_next = dsp;
        // end
    endcase
    dsp_next = dsp + dsp_delta;

    casez (instruction[15:13])
        3'b010:  {rstack_write_enable, rsp_delta} = { 1'b1, 4'b0001 };
        3'b011:  {rstack_write_enable, rsp_delta} = { instruction[5], {instruction[3], instruction[3], instruction[3:2]} };
        default: {rstack_write_enable, rsp_delta} = { 1'b0, 4'b0000 };
        // 3'b010: begin
        //     rstack_write_enable = 1'b1;
        //     rsp_next = rsp + 4'b0001;
        // end
        // 3'b011: begin
        //     rstack_write_enable = instruction[5]; // T→R
        //     rsp_next = rsp + { instruction[3], instruction[3], instruction[3:2] }; // rstack
        // end
        // default: begin
        //     rstack_write_enable = 1'b0;
        //     rsp_next = rsp;
        // end
    endcase
    rsp_next = rsp + rsp_delta;

    casez ({reboot, instruction[15:13], instruction[7] /* R→PC */, |T})
        6'b1_???_?_?: pc_next = 0;
        6'b0_000_?_?,
        6'b0_010_?_?,
        6'b0_001_?_0: pc_next = instruction[12:0];
        6'b0_011_1_?: pc_next = R[13:1];
        default:      pc_next = pc + 1;
    endcase
end

always @(negedge reset or posedge clk)
begin
    if (!reset) begin
        $display("Resetting...");
        reboot <= 1'b1;
        pc  <= 0;
        dsp <= 0;
        T   <= 0;
        rsp <= 0;
    end else begin
        $display("Tick");
        reboot <= 1'b0;
        pc  <= pc_next;
        dsp <= dsp_next;
        T   <= T_next;
        rsp <= rsp_next;
    end
end

endmodule

module fifth_stack(
    input  wire clk, write_enable,
    input  wire [3:0] read_addr, write_addr,
    output wire [15:0] read_data,
    input  wire [15:0] write_data
);

reg [15:0] store[0:31];

always @(posedge clk)
begin
    if (write_enable)
        store[write_addr] <= write_data;
end

assign read_data = store[read_addr];

endmodule

fifth_tb.v
`timescale 1ns/1ps

module fifth_tb();

reg [15:0] ROM[0:1023];
reg [15:0] RAM[0:1023];
reg clk = 0, reset = 1;
always #5 clk = ~clk;
integer t;

initial
begin
    $readmemh("ROM.hex", ROM);

    // $monitor("%3d code_addr = %x",   $time, code_addr);
    // $monitor("%3d mem_address = %x", $time, mem_address);
    // $monitor("%3d instruction = %x", $time, instruction);
    // $monitor("%3d reset = %x",       $time, reset);
    $dumpfile("fifth.vcd");
    $dumpvars(0, cpu);

    clk = 1;
    t = 0;
    reset = 0;
    #1;
    reset = 1;
end

always @(posedge clk)
begin
    t <= t + 1;
    if (t == 10)
    begin
        $finish;
    end
end

wire [12:0] code_addr;
wire [15:0] instruction;
assign instruction = ROM[code_addr];

wire [15:0] mem_address;
wire mem_write_enable;
wire [15:0] mem_data_output;
reg [15:0] mem_data_input;

// Data input: 
// 0x0000 - 0x3fff: ROM
// 0x4000 - 0x7fff: RAM
// 0x8000 - 0xffff: N/A
always @*
begin
    if (mem_address[15:11] == 4'b0000)
        mem_data_input = RAM[mem_address[14:0]];
    else if (mem_address[15:11] == 4'b0001)
        mem_data_input = RAM[mem_address[10:0]];
    else
        mem_data_input = 16'hxxxx;
end

always @(posedge clk)
begin
    if (mem_write_enable)
        RAM[mem_address] = mem_data_output;
end

fifth cpu(
    .clk(clk),
    .reset(reset),
    .code_addr(code_addr),
    .instruction(instruction),
    .mem_address(mem_address),
    .mem_write_enable(mem_write_enable),
    .mem_data_input(mem_data_input),
    .mem_data_output(mem_data_output)
);

//j1 cpu(
//    .clk(clk),
//    .resetq(reset),
//    .code_addr(code_addr),
//    .insn(instruction),
//    .mem_addr(mem_address),
//    .mem_wr(mem_write_enable),
//    .mem_din(mem_data_input),
//    .dout(mem_data_output)
//);

endmodule

fifth.vcd
$date
	Thu Apr 15 23:35:40 2021
$end
$version
	Icarus Verilog
$end
$timescale
	1ps
$end
$scope module fifth_tb $end
$scope module cpu $end
$var wire 1 ! clk $end
$var wire 16 " instruction [15:0] $end
$var wire 16 # mem_address [15:0] $end
$var wire 16 $ mem_data_input [15:0] $end
$var wire 16 % mem_data_output [15:0] $end
$var wire 1 & mem_write_enable $end
$var wire 1 ' reset $end
$var wire 16 ( rstack_write_data [15:0] $end
$var wire 13 ) code_addr [12:0] $end
$var wire 16 * R [15:0] $end
$var wire 16 + N [15:0] $end
$var reg 16 , T [15:0] $end
$var reg 16 - T_next [15:0] $end
$var reg 4 . dsp [3:0] $end
$var reg 4 / dsp_delta [3:0] $end
$var reg 4 0 dsp_next [3:0] $end
$var reg 1 1 dstack_write_enable $end
$var reg 13 2 pc [12:0] $end
$var reg 13 3 pc_next [12:0] $end
$var reg 1 4 reboot $end
$var reg 4 5 rsp [3:0] $end
$var reg 4 6 rsp_delta [3:0] $end
$var reg 4 7 rsp_next [3:0] $end
$var reg 1 8 rstack_write_enable $end
$scope module dstack $end
$var wire 1 ! clk $end
$var wire 4 9 read_addr [3:0] $end
$var wire 16 : read_data [15:0] $end
$var wire 4 ; write_addr [3:0] $end
$var wire 16 < write_data [15:0] $end
$var wire 1 1 write_enable $end
$upscope $end
$scope module rstack $end
$var wire 1 ! clk $end
$var wire 4 = read_addr [3:0] $end
$var wire 16 > read_data [15:0] $end
$var wire 4 ? write_addr [3:0] $end
$var wire 16 @ write_data [15:0] $end
$var wire 1 8 write_enable $end
$upscope $end
$upscope $end
$upscope $end
$enddefinitions $end
#0
$dumpvars
b0 @
b0 ?
bx >
b0 =
b0 <
b0 ;
bx :
b0 9
08
b0 7
b0 6
b0 5
14
b0 3
b0 2
01
b0 0
b0 /
b0 .
b0 -
b0 ,
bx +
bx *
b0 )
b0 (
0'
0&
bz %
bx $
b0 #
b110000000000000 "
1!
$end
#1000
1'
#5000
0!
#10000
b1100000000000010 (
b1100000000000010 @
b100000 #
b100000 -
b1000000000100000 "
b1 )
b1 3
04
1!
#15000
0!
#20000
b110000 #
b110000 -
b1000000000110000 "
b10 )
b10 3
b1 0
b1 ;
11
b1 /
b1100000000000100 (
b1100000000000100 @
b100000 ,
b100000 <
b1 2
1!
#25000
0!
#30000
b100000 #
b100000 -
b110000101000000 "
b11 )
b11 3
b10 0
b10 ;
b110000 (
b110000 @
b100000 +
b100000 :
b110000 ,
b110000 <
b1 .
b1 9
b10 2
1!
#35000
0!
#40000
b100000 (
b100000 @
b1111111111011111 #
b1111111111011111 -
b110011000000000 "
b100 )
b100 3
b0 /
b100000 ,
b100000 <
b110000 +
b110000 :
b10 .
b10 9
b11 2
1!
#45000
0!
#50000
b1111111111011111 (
b1111111111011111 @
b110000000000000 "
b101 )
b101 3
01
b100000 +
b100000 :
b1111111111011111 ,
b1111111111011111 <
b100 2
1!
#55000
0!
#60000
b1111111111111111 #
b1111111111111111 -
b110001000000011 "
b110 )
b110 3
b101 2
1!
#65000
0!
#70000
b1111111111111111 (
b1111111111111111 @
b110000000000000 "
b111 )
b111 3
b1 0
b1 ;
b1111 /
b1111111111111111 ,
b1111111111111111 <
b110 2
1!
#75000
0!
#80000
b1000 )
b1000 3
b0 /
b1 .
b1 9
b111 2
1!
#85000
0!
#90000
b1001 )
b1001 3
b1000 2
1!
#95000
0!
#100000
b1010 )
b1010 3
b1001 2
1!
#105000
0!
#110000
b1010 2
1!
